odoo/addons/base_partition/README.rst
odoo/addons/base_partition/__init__.py
odoo/addons/base_partition/__manifest__.py
odoo/addons/base_partition/i18n/base_partition.pot
odoo/addons/base_partition/i18n/es.po
odoo/addons/base_partition/i18n/fr_BE.pot
odoo/addons/base_partition/i18n/it.po
odoo/addons/base_partition/i18n/zh_CN.po
odoo/addons/base_partition/models/__init__.py
odoo/addons/base_partition/models/models.py
odoo/addons/base_partition/readme/CONTRIBUTORS.md
odoo/addons/base_partition/readme/DESCRIPTION.md
odoo/addons/base_partition/static/description/icon.png
odoo/addons/base_partition/static/description/index.html
odoo/addons/base_partition/tests/__init__.py
odoo/addons/base_partition/tests/test_partition.py
odoo_addon_base_partition-18.0.1.0.0.2.dist-info/METADATA
odoo_addon_base_partition-18.0.1.0.0.2.dist-info/WHEEL
odoo_addon_base_partition-18.0.1.0.0.2.dist-info/top_level.txt
odoo_addon_base_partition-18.0.1.0.0.2.dist-info/RECORD
